pylg/__init__.py
pylg/dummy.py
pylg/loadSettings.py
pylg/pylg.py
pylg/settings.py
PyLg-1.3.3.dist-info/LICENSE.txt
PyLg-1.3.3.dist-info/METADATA
PyLg-1.3.3.dist-info/WHEEL
PyLg-1.3.3.dist-info/top_level.txt
PyLg-1.3.3.dist-info/RECORD
