Metadata-Version: 2.1
Name: PyLg
Version: 1.3.3
Summary: Python module to facilitate and automate the process of writing runtime logs.
Home-page: https://gitlab.wojciechkozlowski.eu/wojtek/PyLg
Author: Wojciech Kozlowski
Author-email: wk@wojciechkozlowski.eu
License: UNKNOWN
Keywords: development log debug trace
Platform: UNKNOWN
Classifier: Development Status :: 4 - Beta
Classifier: Intended Audience :: Developers
Classifier: Topic :: Software Development :: Debuggers
Classifier: License :: OSI Approved :: GNU General Public License v3 or later (GPLv3+)
Classifier: Programming Language :: Python :: 2.7
Classifier: Programming Language :: Python :: 3
